odoo/addons/web_enterprise_admin_expiration_panel/LICENSE
odoo/addons/web_enterprise_admin_expiration_panel/README.rst
odoo/addons/web_enterprise_admin_expiration_panel/__init__.py
odoo/addons/web_enterprise_admin_expiration_panel/__manifest__.py
odoo/addons/web_enterprise_admin_expiration_panel/images/screen.png
odoo/addons/web_enterprise_admin_expiration_panel/static/description/icon.png
odoo/addons/web_enterprise_admin_expiration_panel/static/description/index.html
odoo/addons/web_enterprise_admin_expiration_panel/static/src/js/expiration_panel.js
odoo/addons/web_enterprise_admin_expiration_panel/static/src/js/expiration_panel.xml
odoo_addon_web_enterprise_admin_expiration_panel-16.0.1.0.0.dist-info/METADATA
odoo_addon_web_enterprise_admin_expiration_panel-16.0.1.0.0.dist-info/WHEEL
odoo_addon_web_enterprise_admin_expiration_panel-16.0.1.0.0.dist-info/top_level.txt
odoo_addon_web_enterprise_admin_expiration_panel-16.0.1.0.0.dist-info/RECORD
