Metadata-Version: 2.1
Name: odoo-addon-web_enterprise_admin_expiration_panel
Version: 16.0.1.0.0
Requires-Python: >=3.10
Requires-Dist: odoo>=16.0a,<16.1dev
Summary: Show database expiration panel for Admins only.
Home-page: https://www.mint-system.ch/
License: OPL-1
Author: Mint System GmbH
Classifier: Programming Language :: Python
Classifier: Framework :: Odoo
Classifier: Framework :: Odoo :: 16.0
